.codecov.yml
.codedocs
.gitignore
.travis.yml
CMakeLists.txt
Doxyfile.in
MANIFEST.in
README.md
VERSION
appveyor.yml
coverity_model.c
env.yml
logo.png
setup.py
uploadpypi.sh
.git/COMMIT_EDITMSG
.git/HEAD
.git/config
.git/description
.git/index
.git/packed-refs
.git/hooks/applypatch-msg.sample
.git/hooks/commit-msg.sample
.git/hooks/fsmonitor-watchman.sample
.git/hooks/post-update.sample
.git/hooks/pre-applypatch.sample
.git/hooks/pre-commit.sample
.git/hooks/pre-merge-commit.sample
.git/hooks/pre-push.sample
.git/hooks/pre-rebase.sample
.git/hooks/pre-receive.sample
.git/hooks/prepare-commit-msg.sample
.git/hooks/push-to-checkout.sample
.git/hooks/update.sample
.git/info/exclude
.git/logs/HEAD
.git/logs/refs/heads/master
.git/logs/refs/remotes/origin/HEAD
.git/logs/refs/remotes/origin/master
.git/objects/12/b9ee25ca3500aa43a02bc8b822d21442f38bf4
.git/objects/29/c0d155e80c93ed02538f2ea29d34f175517cc2
.git/objects/2c/6d58e5e5dd87a2fe1aa04b357252723d71fabc
.git/objects/44/ec22d3d03d810a8da24fefc39cc0aa42a89dc1
.git/objects/5c/bb407dce4450765520800bebd1a15455018ee0
.git/objects/pack/pack-0df597067c091b871d1a783a7e1eb5ed05c258d6.idx
.git/objects/pack/pack-0df597067c091b871d1a783a7e1eb5ed05c258d6.pack
.git/refs/heads/master
.git/refs/remotes/origin/HEAD
.git/refs/remotes/origin/master
.github/workflows/ccpp.yml
JASSv1/CI.c
JASSv1/CI.h
JASSv1/GNUmakefile
JASSv1/atire_to_jass_index.c
JASSv1/compress.h
JASSv1/compress_integer_elias_delta_simd.c
JASSv1/compress_integer_elias_delta_simd.h
JASSv1/compress_integer_elias_gamma_simd.c
JASSv1/compress_integer_elias_gamma_simd.h
JASSv1/compress_integer_elias_gamma_simd_vb.cpp
JASSv1/compress_integer_elias_gamma_simd_vb.h
JASSv1/compress_integer_variable_byte.cpp
JASSv1/compress_integer_variable_byte.h
JASSv1/compress_qmx.c
JASSv1/compress_qmx.h
JASSv1/compress_qmx_d4.c
JASSv1/compress_qmx_d4.h
JASSv1/compress_qmx_decompress.c
JASSv1/compress_simple8b.c
JASSv1/compress_simple8b.h
JASSv1/compress_variable_byte.c
pyjass.egg-info/PKG-INFO
pyjass.egg-info/SOURCES.txt
pyjass.egg-info/dependency_links.txt
pyjass.egg-info/requires.txt
pyjass.egg-info/top_level.txt
