Metadata-Version: 1.2
Name: pyjass
Version: 0.2a7
Summary: The JASS experimental Score-at-a-Time search engine.
Home-page: UNKNOWN
Author: Andrew Trotman
Author-email: andrew@cs.otago.ac.nz
License: UNKNOWN
Project-URL: Bug Reports, https://github.com/andrewtrotman/JASSv2/issues
Project-URL: Source, https://github.com/andrewtrotman/JASSv2
Keywords: search engine,search tool,jass,SaaT
Platform: UNKNOWN
Classifier: Programming Language :: Python :: 3
Classifier: Operating System :: MacOS :: MacOS X
Classifier: Operating System :: POSIX :: Linux
Requires-Python: >=3.4
